rocksdbdict/__init__.py
rocksdbdict/rocksdbdict.py
rocksdbdict-0.8.0.dist-info/LICENSE
rocksdbdict-0.8.0.dist-info/WHEEL
rocksdbdict-0.8.0.dist-info/METADATA
rocksdbdict-0.8.0.dist-info/RECORD
