Metadata-Version: 2.1
Name: rocksdbdict
Version: 0.8.0
Summary: 
License: MIT
Author: Adam Marples
Author-email: adammarples@gmail.com
Requires-Python: >=3.7,<4.0
Classifier: License :: OSI Approved :: MIT License
Classifier: Programming Language :: Python :: 3
Classifier: Programming Language :: Python :: 3.10
Classifier: Programming Language :: Python :: 3.7
Classifier: Programming Language :: Python :: 3.8
Classifier: Programming Language :: Python :: 3.9
Requires-Dist: faust-streaming-rocksdb (>=0.8.0,<0.9.0)
